mapsi/__init__.py
mapsi/cli.py
mapsi/core.py
mapsi/__pycache__/__init__.cpython-37.pyc
mapsi/assets/mapsi_big.png
mapsi/assets/mapsi_big.pxz
mapsi/assets/mapsi_fav.ico
mapsi/assets/mapsi_fav.png
mapsi/assets/mapsi_fav.pxz
mapsi/build_files/main.py
mapsi/build_files/mapsi/__init__.py
mapsi/build_files/mapsi/core.py
mapsi/build_files/mapsi/router.py
mapsi/build_files/mapsi/util.py
mapsi/build_files/mapsi/vdom.py
mapsi/template_files/App.mapsi
mapsi/template_files/main.py
mapsi/template_files/public/favicon.ico
mapsi/template_files/public/index.html
mapsi/template_files/public/mapsi.css
mapsi/template_files/src/router.py
mapsi/template_files/src/assets/mapsi_big.png
mapsi/template_files/src/components/HelloWorld.mapsi
mapsi/template_files/src/views/Counter.mapsi
mapsi/template_files/src/views/Hello.mapsi
mapsi/template_files/src/views/Home.mapsi
mapsi/template_files/src/views/Tabular.mapsi
mapsipy-2021.4.22.post3.dist-info/LICENSE
mapsipy-2021.4.22.post3.dist-info/METADATA
mapsipy-2021.4.22.post3.dist-info/WHEEL
mapsipy-2021.4.22.post3.dist-info/entry_points.txt
mapsipy-2021.4.22.post3.dist-info/top_level.txt
mapsipy-2021.4.22.post3.dist-info/RECORD
