Metadata-Version: 2.1
Name: mapsipy
Version: 2021.4.22.post3
Summary: MVVM UI Framework for Python and Brython
Home-page: https://github.com/eseunghwan/mapsipy
Author: eseunghwan
Author-email: shlee0920@naver.com
License: MIT license
Keywords: mapsipy,brython,mvvm
Platform: UNKNOWN
Classifier: Development Status :: 2 - Pre-Alpha
Classifier: Intended Audience :: Developers
Classifier: License :: OSI Approved :: MIT License
Classifier: Natural Language :: Korean
Classifier: Programming Language :: Python :: 3
Classifier: Programming Language :: Python :: 3.5
Classifier: Programming Language :: Python :: 3.6
Classifier: Programming Language :: Python :: 3.7
Classifier: Programming Language :: Python :: 3.8
Requires-Python: >=3.7
Requires-Dist: brython
Requires-Dist: lxml
